journal_search/__init__.py
journal_search/__main__.py
journal_search/utils.py
journal_search/assets/index.14cf70d2.css
journal_search/assets/index.b31b0d13.js
journal_search/assets/index.html
journal_search/assets/logo.svg
journal_search/data/ccf2019.csv
journal_search-1.0.0.dist-info/LICENSE
journal_search-1.0.0.dist-info/METADATA
journal_search-1.0.0.dist-info/WHEEL
journal_search-1.0.0.dist-info/entry_points.txt
journal_search-1.0.0.dist-info/top_level.txt
journal_search-1.0.0.dist-info/RECORD
