Metadata-Version: 2.1
Name: journal-search
Version: 1.0.0
Summary: A tool for query journal/conference level information
Author-email: Kevin2li <kevin2li@qq.com>
License: MIT License        
Project-URL: Homepage, https://github.com/kevin2li/journal_search
Keywords: toolkit,pdf,ppt
Classifier: License :: OSI Approved :: MIT License
Classifier: Programming Language :: Python
Classifier: Programming Language :: Python :: 3
Requires-Python: >=3.9
License-File: LICENSE
Requires-Dist: flask[async]
Requires-Dist: flask-cors
Requires-Dist: pandas
Requires-Dist: icecream
Requires-Dist: parsel
Requires-Dist: loguru
Requires-Dist: playwright
Requires-Dist: tenacity
Provides-Extra: dev
Requires-Dist: pip-tools ; extra == 'dev'
Requires-Dist: pytest ; extra == 'dev'
